icon_registration/__init__.py
icon_registration/config.py
icon_registration/data.py
icon_registration/inverseConsistentNet.py
icon_registration/itk_wrapper.py
icon_registration/losses.py
icon_registration/mermaidlite.py
icon_registration/monai_wrapper.py
icon_registration/network_wrappers.py
icon_registration/networks.py
icon_registration/test_utils.py
icon_registration/train.py
icon_registration/visualize.py
icon_registration/pretrained_models/HCP_brain.py
icon_registration/pretrained_models/OAI_knees.py
icon_registration/pretrained_models/__init__.py
icon_registration/pretrained_models/lung_ct.py
icon_registration-1.1.6.dist-info/licenses/LICENSE
icon_registration-1.1.6.dist-info/METADATA
icon_registration-1.1.6.dist-info/WHEEL
icon_registration-1.1.6.dist-info/top_level.txt
icon_registration-1.1.6.dist-info/RECORD
