Metadata-Version: 2.4
Name: icon_registration
Version: 1.1.6
Summary: A package for image registration regularized by inverse consistency
Home-page: https://github.com/uncbiag/ICON
Author: Hastings Greer
Author-email: t@hgreer.com
Project-URL: Bug Tracker, https://github.com/uncbiag/ICON/issues
Classifier: Programming Language :: Python :: 3
Classifier: License :: OSI Approved :: Apache Software License
Classifier: Operating System :: POSIX :: Linux
Requires-Python: >=3.4
License-File: LICENSE
Requires-Dist: torch
Requires-Dist: torchvision
Requires-Dist: tensorboard
Requires-Dist: tqdm
Requires-Dist: matplotlib
Requires-Dist: footsteps>=0.1.6
Requires-Dist: itk>=5.3a
Requires-Dist: girder_client==3.1.8
Dynamic: license-file
